epson_projector/__init__.py
epson_projector/base_connection.py
epson_projector/const.py
epson_projector/error.py
epson_projector/lock.py
epson_projector/projector.py
epson_projector/projector_http.py
epson_projector/projector_serial.py
epson_projector/projector_tcp.py
epson_projector/timeout.py
epson_projector/version.py
epson_projector-0.6.0.dist-info/licenses/LICENSE
epson_projector-0.6.0.dist-info/METADATA
epson_projector-0.6.0.dist-info/WHEEL
epson_projector-0.6.0.dist-info/top_level.txt
epson_projector-0.6.0.dist-info/RECORD
