Metadata-Version: 2.4
Name: epson_projector
Version: 0.6.0
Summary: Epson projector support for Python
Home-page: https://github.com/pszafer/epson_projector
Author: Paweł Szafer
Author-email: pszafer@gmail.com
License: MIT
Keywords: epson,projector
Classifier: Programming Language :: Python :: 3
Classifier: License :: OSI Approved :: MIT License
Classifier: Operating System :: OS Independent
Classifier: Topic :: Software Development :: Libraries :: Python Modules
License-File: LICENSE
Requires-Dist: aiohttp>=3.3.0
Requires-Dist: pyserial-asyncio-fast>=0.16
Dynamic: author
Dynamic: author-email
Dynamic: classifier
Dynamic: description
Dynamic: description-content-type
Dynamic: home-page
Dynamic: keywords
Dynamic: license
Dynamic: license-file
Dynamic: requires-dist
Dynamic: summary
